<?xml version='1.0' encoding='utf-8'?>
<TextureAtlas imagePath="metal.png">
<SubTexture name="metal static0000" x="0" y="101" width="27" height="40" frameX="-19" frameY="-15" frameWidth="64" frameHeight="64" />
<SubTexture name="metal start0000" x="27" y="101" width="28" height="40" frameX="-18" frameY="-15" frameWidth="64" frameHeight="64" />
<SubTexture name="metal start0001" x="55" y="101" width="27" height="40" frameX="-19" frameY="-15" frameWidth="64" frameHeight="64" />
<SubTexture name="metal start0002" x="27" y="101" width="28" height="40" frameX="-18" frameY="-15" frameWidth="64" frameHeight="64" />
<SubTexture name="metal start0003" x="55" y="101" width="27" height="40" frameX="-19" frameY="-15" frameWidth="64" frameHeight="64" />
<SubTexture name="metal start0004" x="0" y="101" width="27" height="40" frameX="-19" frameY="-15" frameWidth="64" frameHeight="64" />
<SubTexture name="metal start0005" x="82" y="101" width="27" height="40" frameX="-19" frameY="-15" frameWidth="64" frameHeight="64" />
<SubTexture name="metal start0006" x="109" y="101" width="28" height="40" frameX="-20" frameY="-15" frameWidth="64" frameHeight="64" />
<SubTexture name="metal start0007" x="167" y="0" width="27" height="38" frameX="-21" frameY="-17" frameWidth="64" frameHeight="64" />
<SubTexture name="metal start0008" x="56" y="0" width="25" height="47" frameX="-23" frameY="-8" frameWidth="64" frameHeight="64" />
<SubTexture name="metal start0009" x="81" y="0" width="25" height="47" frameX="-23" frameY="-8" frameWidth="64" frameHeight="64" />
<SubTexture name="metal start0010" x="0" y="54" width="30" height="47" frameX="-18" frameY="-8" frameWidth="64" frameHeight="64" />
<SubTexture name="metal start0011" x="81" y="0" width="25" height="47" frameX="-23" frameY="-8" frameWidth="64" frameHeight="64" />
<SubTexture name="metal right0000" x="30" y="54" width="34" height="47" frameX="-21" frameY="-8" frameWidth="64" frameHeight="64" />
<SubTexture name="metal right0001" x="64" y="54" width="27" height="47" frameX="-26" frameY="-8" frameWidth="64" frameHeight="64" />
<SubTexture name="metal left0000" x="132" y="0" width="35" height="42" frameX="-11" frameY="-10" frameWidth="64" frameHeight="64" />
<SubTexture name="metal left0001" x="132" y="42" width="35" height="42" frameX="-12" frameY="-10" frameWidth="64" frameHeight="64" />
<SubTexture name="metal up0000" x="0" y="0" width="30" height="54" frameX="-18" frameY="-1" frameWidth="64" frameHeight="64" />
<SubTexture name="metal up0001" x="30" y="0" width="26" height="51" frameX="-22" frameY="-4" frameWidth="64" frameHeight="64" />
<SubTexture name="metal up0002" x="106" y="0" width="26" height="47" frameX="-22" frameY="-9" frameWidth="64" frameHeight="64" />
<SubTexture name="metal up0003" x="106" y="47" width="26" height="47" frameX="-22" frameY="-9" frameWidth="64" frameHeight="64" />
<SubTexture name="metal down0000" x="0" y="141" width="33" height="35" frameX="-14" frameY="-21" frameWidth="64" frameHeight="64" />
<SubTexture name="metal down0001" x="137" y="101" width="25" height="40" frameX="-22" frameY="-17" frameWidth="64" frameHeight="64" />
</TextureAtlas>
